buzz/__init__.py
buzz/__main__.py
buzz/__version__.py
buzz/action.py
buzz/assets.py
buzz/buzz.py
buzz/cache.py
buzz/cli.py
buzz/conn.py
buzz/cuda_setup.py
buzz/dialogs.py
buzz/file_transcriber_queue_worker.py
buzz/locale.py
buzz/model_loader.py
buzz/paths.py
buzz/recording.py
buzz/schema.sql
buzz/transformers_whisper.py
buzz/translator.py
buzz/whisper_audio.py
buzz/assets/add_FILL0_wght700_GRAD0_opsz48.svg
buzz/assets/buzz-banner.jpg
buzz/assets/buzz-icon-1024.png
buzz/assets/buzz.icns
buzz/assets/buzz.ico
buzz/assets/buzz.png
buzz/assets/buzz.svg
buzz/assets/cancel_FILL0_wght700_GRAD0_opsz48.svg
buzz/assets/delete_FILL0_wght700_GRAD0_opsz48.svg
buzz/assets/file_download_black_24dp.svg
buzz/assets/info-circle.svg
buzz/assets/mic_FILL0_wght700_GRAD0_opsz48.svg
buzz/assets/open_in_full_FILL0_wght700_GRAD0_opsz48.svg
buzz/assets/pause_black_24dp.svg
buzz/assets/play_arrow_black_24dp.svg
buzz/assets/redo_FILL0_wght700_GRAD0_opsz48.svg
buzz/assets/resize_black.svg
buzz/assets/speaker-identification.svg
buzz/assets/translate_black.svg
buzz/assets/undo_FILL0_wght700_GRAD0_opsz48.svg
buzz/assets/url.svg
buzz/assets/visibility_FILL0_wght700_GRAD0_opsz48.svg
buzz/assets/visibility_off_FILL0_wght700_GRAD0_opsz48.svg
buzz/assets/icons/color-background.svg
buzz/assets/icons/fullscreen.svg
buzz/assets/icons/gui-text-color.svg
buzz/assets/icons/new-window.svg
buzz/db/__init__.py
buzz/db/db.py
buzz/db/helpers.py
buzz/db/migrator.py
buzz/db/dao/__init__.py
buzz/db/dao/dao.py
buzz/db/dao/transcription_dao.py
buzz/db/dao/transcription_segment_dao.py
buzz/db/entity/__init__.py
buzz/db/entity/entity.py
buzz/db/entity/transcription.py
buzz/db/entity/transcription_segment.py
buzz/db/service/__init__.py
buzz/db/service/transcription_service.py
buzz/locale/ca_ES/LC_MESSAGES/buzz.po
buzz/locale/da_DK/LC_MESSAGES/buzz.po
buzz/locale/de_DE/LC_MESSAGES/buzz.po
buzz/locale/en_US/LC_MESSAGES/buzz.po
buzz/locale/es_ES/LC_MESSAGES/buzz.po
buzz/locale/it_IT/LC_MESSAGES/buzz.po
buzz_captions-1.4.3.dist-info/METADATA
buzz_captions-1.4.3.dist-info/WHEEL
buzz_captions-1.4.3.dist-info/entry_points.txt
buzz_captions-1.4.3.dist-info/licenses/LICENSE
buzz_captions-1.4.3.dist-info/RECORD
