Metadata-Version: 2.4
Name: buzz-captions
Version: 1.4.3
Author-email: Chidi Williams <williamschidi1@gmail.com>
License: MIT
License-File: LICENSE
Requires-Python: <3.13,>=3.12
Requires-Dist: accelerate<2,>=1.12.0
Requires-Dist: bitsandbytes>=0.45.0; sys_platform != 'darwin' or platform_machine != 'x86_64'
Requires-Dist: certifi==2025.11.12
Requires-Dist: cmake<5,>=4.2.0
Requires-Dist: coverage==7.12.0
Requires-Dist: ctranslate2<5,>=4.6.2; sys_platform != 'darwin'
Requires-Dist: ctranslate2<5,>=4.6.2; sys_platform == 'darwin' and platform_machine == 'arm64'
Requires-Dist: ctranslate2==4.3.1; sys_platform == 'darwin' and platform_machine == 'x86_64'
Requires-Dist: darkdetect<0.9,>=0.8.0
Requires-Dist: dataclasses-json<0.7,>=0.6.4
Requires-Dist: datasets>=4.4.1
Requires-Dist: diffq<0.3,>=0.2.4
Requires-Dist: dora-search<0.2,>=0.1.12
Requires-Dist: einops<0.9,>=0.8.1
Requires-Dist: faster-whisper<2,>=1.2.1
Requires-Dist: flake8<8,>=7.1.2
Requires-Dist: hatchling>=1.28.0
Requires-Dist: hf-xet<2,>=1.1.5
Requires-Dist: humanize<5,>=4.4.0
Requires-Dist: hydra-colorlog<2,>=1.2.0
Requires-Dist: hydra-core<2,>=1.3.2
Requires-Dist: julius<0.3,>=0.2.7
Requires-Dist: keyring<26,>=25.0.0
Requires-Dist: lameenc<2,>=1.8.1
Requires-Dist: lhotse==1.32.1
Requires-Dist: museval<0.5,>=0.4.1
Requires-Dist: mypy<2,>=1.15.0
Requires-Dist: nemo-toolkit[asr]==2.5.3; sys_platform != 'darwin' or platform_machine != 'x86_64'
Requires-Dist: nltk>=3.9.2
Requires-Dist: numpy<2,>=1.21.2
Requires-Dist: nvidia-cudnn-cu12<10,>=9; sys_platform != 'darwin'
Requires-Dist: onnx>=1.20.0
Requires-Dist: onnxruntime==1.18.1
Requires-Dist: openai-whisper==20250625
Requires-Dist: openai<2,>=1.14.2
Requires-Dist: openunmix<2,>=1.3.0
Requires-Dist: peft<1,>=0.14.0
Requires-Dist: platformdirs<5,>=4.2.1
Requires-Dist: polib<2,>=1.2.0
Requires-Dist: posthog<4,>=3.23.0
Requires-Dist: pyqt6-qt6==6.9.1
Requires-Dist: pyqt6-sip==13.10.2
Requires-Dist: pyqt6==6.9.1
Requires-Dist: pyyaml<7,>=6.0.2
Requires-Dist: requests<3,>=2.31.0
Requires-Dist: sounddevice<0.6,>=0.5.3
Requires-Dist: soundfile<0.14,>=0.13.1
Requires-Dist: srt-equalizer<0.2,>=0.1.10
Requires-Dist: stable-ts<3,>=2.19.1
Requires-Dist: submitit<2,>=1.5.2
Requires-Dist: torch==2.2.2; sys_platform == 'darwin' and platform_machine == 'x86_64'
Requires-Dist: torch==2.8.0; sys_platform != 'darwin'
Requires-Dist: torch==2.8.0; sys_platform == 'darwin' and platform_machine == 'arm64'
Requires-Dist: torch>=2.2.2
Requires-Dist: torchaudio==2.2.2; sys_platform == 'darwin' and platform_machine == 'x86_64'
Requires-Dist: torchaudio==2.8.0; sys_platform != 'darwin'
Requires-Dist: torchaudio==2.8.0; sys_platform == 'darwin' and platform_machine == 'arm64'
Requires-Dist: torchaudio>=2.2.2
Requires-Dist: torchcodec>=0.9.0; sys_platform != 'darwin' or platform_machine != 'x86_64'
Requires-Dist: tqdm<5,>=4.67.1
Requires-Dist: transformers<5,>=4.53
Requires-Dist: treetable<0.3,>=0.2.5
Requires-Dist: urllib3<3,>=2.6.0
Requires-Dist: uroman>=1.3.1.1
Requires-Dist: vulkan<2,>=1.3.275.1
Requires-Dist: yt-dlp<2026,>=2025.11.12
